bigdata_vanhaydoi_framework/__init__.py
bigdata_vanhaydoi_framework/number_algorithms.py
bigdata_vanhaydoi_framework-0.2.0.dist-info/METADATA
bigdata_vanhaydoi_framework-0.2.0.dist-info/WHEEL
bigdata_vanhaydoi_framework-0.2.0.dist-info/top_level.txt
bigdata_vanhaydoi_framework-0.2.0.dist-info/RECORD
