Metadata-Version: 2.4
Name: bigdata_vanhaydoi_framework
Version: 0.2.0
Summary: A short description of your project
Home-page: https://github.com/yourusername/my_project
Author: Vanhaydoi
Author-email: nguyenduyvanhaydoi1512@gmail.com
License: MIT
Classifier: Programming Language :: Python :: 3
Classifier: License :: OSI Approved :: MIT License
Classifier: Operating System :: OS Independent
Requires-Dist: requests
